getnet_sdk/__init__.py
getnet_sdk/client.py
getnet_sdk-0.1.2.dist-info/METADATA
getnet_sdk-0.1.2.dist-info/WHEEL
getnet_sdk-0.1.2.dist-info/top_level.txt
getnet_sdk-0.1.2.dist-info/RECORD
