Metadata-Version: 2.4
Name: getnet_sdk
Version: 0.1.2
Summary: Python SDK for integrating with the Getnet payment API
Home-page: https://github.com/ninjaroot-509/getnet_sdk
Author: ninjaroot-509
Project-URL: Source, https://github.com/ninjaroot-509/getnet_sdk
Classifier: Programming Language :: Python :: 3
Classifier: License :: OSI Approved :: MIT License
Classifier: Operating System :: OS Independent
Requires-Python: >=3.6
Requires-Dist: requests
Dynamic: author
Dynamic: classifier
Dynamic: description
Dynamic: description-content-type
Dynamic: home-page
Dynamic: project-url
Dynamic: requires-dist
Dynamic: requires-python
Dynamic: summary
